time_util_wj.py
time_util_wj-1.0.4.dist-info/METADATA
time_util_wj-1.0.4.dist-info/WHEEL
time_util_wj-1.0.4.dist-info/top_level.txt
time_util_wj-1.0.4.dist-info/RECORD
