Metadata-Version: 2.1
Name: time-util-wj
Version: 1.0.4
Summary: 提供了各种时间转换的方法
Home-page: https://github.com/wangjie-jason/time_utils
Author: WangJie
Author-email: 1641540482@qq.com
License: UNKNOWN
Platform: UNKNOWN
Classifier: Programming Language :: Python :: 3
Classifier: License :: OSI Approved :: Apache Software License
Classifier: Operating System :: OS Independent
